LICENSE.txt
README.md
setup.cfg
setup.py
Topsis_Mayank_102097021/topsis.py
Topsis_Mayank_102097021.egg-info/PKG-INFO
Topsis_Mayank_102097021.egg-info/SOURCES.txt
Topsis_Mayank_102097021.egg-info/dependency_links.txt
Topsis_Mayank_102097021.egg-info/entry_points.txt
Topsis_Mayank_102097021.egg-info/requires.txt
Topsis_Mayank_102097021.egg-info/top_level.txt