Metadata-Version: 2.1
Name: Topsis-Mayank-102097021
Version: 1.0.0
Summary: Package to calculate Topsis Score
Home-page: UNKNOWN
Author: Mayank Kumar
License: MIT
Platform: UNKNOWN
Classifier: Programming Language :: Python :: 3
Classifier: License :: OSI Approved :: MIT License
Classifier: Operating System :: OS Independent
License-File: LICENSE.txt
